solidityParserPlus/__init__.py
solidityParserPlus/__main__.py
solidityParserPlus/parserPlus.py
solidityParserPlus/solidity_antlr4/SolidityLexer.py
solidityParserPlus/solidity_antlr4/SolidityListener.py
solidityParserPlus/solidity_antlr4/SolidityParser.py
solidityParserPlus/solidity_antlr4/SolidityVisitor.py
solidityParserPlus/solidity_antlr4/__init__.py
solidityParserPlus-0.0.4.dist-info/METADATA
solidityParserPlus-0.0.4.dist-info/WHEEL
solidityParserPlus-0.0.4.dist-info/top_level.txt
solidityParserPlus-0.0.4.dist-info/RECORD
